{"name":"fd-tutorial-bloom-perspective","id":"eeef10a0-93f8-11ec-92ae-414bd8007797","categories":[{"id":5,"name":"FlaggedUser","labels":["FlaggedUser"],"properties":[{"name":"louvainCommunityId","exclude":false,"dataType":"bigint"},{"name":"wccId","exclude":false,"dataType":"bigint"},{"name":"fraudRisk","exclude":false,"dataType":"bigint"},{"name":"fraudMoneyTransfer","exclude":false,"dataType":"bigint"},{"name":"firstChargebackMtDate","exclude":false,"dataType":"Date"},{"name":"moneyTransferErrorCancelAmount","exclude":false,"dataType":"number"},{"name":"guid","exclude":false,"dataType":"string"},{"name":"partOfCommunity","exclude":false,"dataType":"bigint"},{"name":"sharedIdsDegree","exclude":false,"dataType":"number"},{"name":"communitySize","exclude":false,"dataType":"bigint"},{"name":"p2pSentPageRank","exclude":false,"dataType":"number"},{"name":"p2pSharedCardPageRank","exclude":false,"dataType":"number"},{"name":"p2pReceivedWeightedPageRank","exclude":false,"dataType":"number"},{"name":"ipDegree","exclude":false,"dataType":"number"},{"name":"cardDegree","exclude":false,"dataType":"number"},{"name":"p2pReceivedWeightedDegree","exclude":false,"dataType":"number"},{"name":"deviceDegree","exclude":false,"dataType":"number"}],"createdAt":1645545791154,"lastEditedAt":1664287706565,"color":"#F16667","size":0.5,"icon":"DB188874-D25F-4B34-A296-E5E950072319","captionKeys":["0_CATEGORY_NAME_CAPTION_KEY","fraudMoneyTransfer","fraudRisk"]},{"id":6,"name":"FraudRiskUser","labels":["FraudRiskUser"],"properties":[{"name":"fraudMoneyTransfer","exclude":false,"dataType":"bigint"},{"name":"firstChargebackMtDate","exclude":false,"dataType":"Date"},{"name":"fraudRisk","exclude":false,"dataType":"bigint"},{"name":"moneyTransferErrorCancelAmount","exclude":false,"dataType":"number"},{"name":"louvainCommunityId","exclude":false,"dataType":"bigint"},{"name":"wccId","exclude":false,"dataType":"bigint"},{"name":"guid","exclude":false,"dataType":"string"},{"name":"p2pReceivedPageRank","exclude":false,"dataType":"number"},{"name":"p2pReceivedWeightedPageRank","exclude":false,"dataType":"number"},{"name":"ipDegree","exclude":false,"dataType":"number"},{"name":"p2pReversedSharedCardDegree","exclude":false,"dataType":"number"},{"name":"p2pReceivedWeightedDegree","exclude":false,"dataType":"number"},{"name":"p2pSentDegree","exclude":false,"dataType":"number"},{"name":"communitySize","exclude":false,"dataType":"bigint"},{"name":"p2pSentWeightedDegree","exclude":false,"dataType":"number"},{"name":"p2pSentWeightedPageRank","exclude":false,"dataType":"number"},{"name":"p2pReceivedDegree","exclude":false,"dataType":"number"},{"name":"p2pSharedCardPageRank","exclude":false,"dataType":"number"},{"name":"cardDegree","exclude":false,"dataType":"number"},{"name":"partOfCommunity","exclude":false,"dataType":"bigint"},{"name":"p2pSharedCardDegree","exclude":false,"dataType":"number"},{"name":"sharedIdsDegree","exclude":false,"dataType":"number"},{"name":"p2pSentPageRank","exclude":false,"dataType":"number"},{"name":"deviceDegree","exclude":false,"dataType":"number"},{"name":"p2pReversedSharedCardPageRank","exclude":false,"dataType":"number"}],"createdAt":1645545791154,"lastEditedAt":1664287555302,"color":"#8e2d2d","size":0.5,"icon":"DB188874-D25F-4B34-A296-E5E950072319","captionKeys":["0_CATEGORY_NAME_CAPTION_KEY","fraudMoneyTransfer","fraudRisk"]},{"id":8,"name":"PredictedFraudRisk","labels":["PredictedFraudRisk"],"properties":[{"name":"deviceDegree","exclude":false,"dataType":"number"},{"name":"predictedProbability","exclude":false,"dataType":"number"},{"name":"ipDegree","exclude":false,"dataType":"number"},{"name":"cardDegree","exclude":false,"dataType":"number"},{"name":"p2pReceivedWeightedPageRank","exclude":false,"dataType":"number"},{"name":"p2pReceivedWeightedDegree","exclude":false,"dataType":"number"},{"name":"p2pSharedCardPageRank","exclude":false,"dataType":"number"},{"name":"p2pSentPageRank","exclude":false,"dataType":"number"},{"name":"communitySize","exclude":false,"dataType":"bigint"},{"name":"partOfCommunity","exclude":false,"dataType":"bigint"},{"name":"sharedIdsDegree","exclude":false,"dataType":"number"},{"name":"fraudMoneyTransfer","exclude":false,"dataType":"bigint"},{"name":"firstChargebackMtDate","exclude":false,"dataType":"Date"},{"name":"fraudRisk","exclude":false,"dataType":"bigint"},{"name":"moneyTransferErrorCancelAmount","exclude":false,"dataType":"number"},{"name":"louvainCommunityId","exclude":false,"dataType":"bigint"},{"name":"wccId","exclude":false,"dataType":"bigint"},{"name":"guid","exclude":false,"dataType":"string"}],"createdAt":1664287555358,"lastEditedAt":1664287555358,"color":"#8DCC93","size":2,"icon":"DB188874-D25F-4B34-A296-E5E950072319","captionKeys":["0_CATEGORY_NAME_CAPTION_KEY","predictedProbability"]},{"id":4,"name":"User","labels":["User"],"properties":[{"name":"fraudMoneyTransfer","exclude":false,"dataType":"bigint"},{"name":"firstChargebackMtDate","exclude":false,"dataType":"Date"},{"name":"fraudRisk","exclude":false,"dataType":"bigint"},{"name":"moneyTransferErrorCancelAmount","exclude":false,"dataType":"number"},{"name":"louvainCommunityId","exclude":false,"dataType":"bigint"},{"name":"wccId","exclude":false,"dataType":"bigint"},{"name":"guid","exclude":false,"dataType":"string"},{"name":"p2pReceivedPageRank","exclude":false,"dataType":"number"},{"name":"p2pReceivedWeightedPageRank","exclude":false,"dataType":"number"},{"name":"ipDegree","exclude":false,"dataType":"number"},{"name":"p2pReversedSharedCardDegree","exclude":false,"dataType":"number"},{"name":"p2pReceivedWeightedDegree","exclude":false,"dataType":"number"},{"name":"p2pSentDegree","exclude":false,"dataType":"number"},{"name":"communitySize","exclude":false,"dataType":"bigint"},{"name":"p2pSentWeightedDegree","exclude":false,"dataType":"number"},{"name":"p2pSentWeightedPageRank","exclude":false,"dataType":"number"},{"name":"p2pReceivedDegree","exclude":false,"dataType":"number"},{"name":"p2pSharedCardPageRank","exclude":false,"dataType":"number"},{"name":"cardDegree","exclude":false,"dataType":"number"},{"name":"partOfCommunity","exclude":false,"dataType":"bigint"},{"name":"p2pSharedCardDegree","exclude":false,"dataType":"number"},{"name":"sharedIdsDegree","exclude":false,"dataType":"number"},{"name":"p2pSentPageRank","exclude":false,"dataType":"number"},{"name":"deviceDegree","exclude":false,"dataType":"number"},{"name":"p2pReversedSharedCardPageRank","exclude":false,"dataType":"number"}],"createdAt":1645545791154,"lastEditedAt":1645817687735,"color":"#F79767","size":0.5,"icon":"DB188874-D25F-4B34-A296-E5E950072319","captionKeys":["0_CATEGORY_NAME_CAPTION_KEY","fraudMoneyTransfer","fraudRisk"]},{"id":1,"name":"Card","labels":["Card"],"properties":[{"name":"fraudRiskDegree","exclude":false,"dataType":"number"},{"name":"fraudRiskRatio","exclude":false,"dataType":"number"},{"name":"flaggedRatio","exclude":false,"dataType":"number"},{"name":"louvainCommunityId","exclude":false,"dataType":"bigint"},{"name":"degree","exclude":false,"dataType":"number"},{"name":"flaggedDegree","exclude":false,"dataType":"number"},{"name":"guid","exclude":false,"dataType":"string"},{"name":"cardType","exclude":false,"dataType":"string"},{"name":"level","exclude":false,"dataType":"string"}],"createdAt":1645545791154,"lastEditedAt":1645545971288,"color":"#4C8EDA","size":0.25,"icon":"3D9A7535-B81F-4597-8F6C-001730295B10","captionKeys":["0_CATEGORY_NAME_CAPTION_KEY","degree"]},{"id":2,"name":"Device","labels":["Device"],"properties":[{"name":"fraudRiskDegree","exclude":false,"dataType":"number"},{"name":"fraudRiskRatio","exclude":false,"dataType":"number"},{"name":"flaggedDegree","exclude":false,"dataType":"number"},{"name":"flaggedRatio","exclude":false,"dataType":"number"},{"name":"guid","exclude":false,"dataType":"string"},{"name":"os","exclude":false,"dataType":"string"},{"name":"degree","exclude":false,"dataType":"number"},{"name":"device","exclude":false,"dataType":"string"},{"name":"louvainCommunityId","exclude":false,"dataType":"bigint"}],"createdAt":1645545791154,"lastEditedAt":1645545981454,"color":"#C990C0","size":0.25,"icon":"9B83DEC9-D1A1-4D1E-A74E-57FCCD5436BA","captionKeys":["0_CATEGORY_NAME_CAPTION_KEY","degree"]},{"id":3,"name":"IP","labels":["IP"],"properties":[{"name":"fraudRiskRatio","exclude":false,"dataType":"number"},{"name":"flaggedRatio","exclude":false,"dataType":"number"},{"name":"fraudRiskDegree","exclude":false,"dataType":"number"},{"name":"degree","exclude":false,"dataType":"number"},{"name":"flaggedDegree","exclude":false,"dataType":"number"},{"name":"guid","exclude":false,"dataType":"string"}],"createdAt":1645545791154,"lastEditedAt":1645545985158,"color":"#D9C8AE","size":0.25,"icon":"784FAF1E-E507-4967-9DE4-4B25F1F5125C","captionKeys":["0_CATEGORY_NAME_CAPTION_KEY","degree"],"styleRules":[{"id":"rule:1664295654488","type":"range","size":1,"minSize":1,"maxSize":2,"minColor":"#a48d6d","midColor":"#dbc8ad","maxColor":"#f2ead4","minPoint":"2","maxPoint":"8772","applyColor":true,"applySize":false,"applyCaption":false,"captionKeys":["0_CATEGORY_NAME_CAPTION_KEY"],"color":"#a68f6f","isTimeZoneConvertEnabled":false,"selectedTimeZone":"Z","basedOn":"degree_number","valuesMapper":[],"existingValues":[],"maxSizeValue":"8772","maxColorValue":"8772","minSizeValue":"2","minColorValue":"1","conditionValue":2,"rangeValue":8773,"condition":"between","midColorValue":"30"}]},{"id":7,"name":"FraudSharedId","labels":["FraudSharedId"],"properties":[{"name":"fraudRiskDegree","exclude":false,"dataType":"number"},{"name":"fraudRiskRatio","exclude":false,"dataType":"number"},{"name":"flaggedRatio","exclude":false,"dataType":"number"},{"name":"louvainCommunityId","exclude":false,"dataType":"bigint"},{"name":"degree","exclude":false,"dataType":"number"},{"name":"flaggedDegree","exclude":false,"dataType":"number"},{"name":"guid","exclude":false,"dataType":"string"},{"name":"cardType","exclude":false,"dataType":"string"},{"name":"level","exclude":false,"dataType":"string"},{"name":"os","exclude":false,"dataType":"string"},{"name":"device","exclude":false,"dataType":"string"}],"createdAt":1645545791154,"lastEditedAt":1664287555337,"color":"#8DCC93","size":1,"icon":"no-icon","captionKeys":["0_CATEGORY_NAME_CAPTION_KEY","fraudRiskDegree"]}],"labels":{"Card":[{"propertyKey":"fraudRiskDegree","type":"Card","dataType":"number"},{"propertyKey":"fraudRiskRatio","type":"Card","dataType":"number"},{"propertyKey":"flaggedRatio","type":"Card","dataType":"number"},{"propertyKey":"louvainCommunityId","type":"Card","dataType":"bigint"},{"propertyKey":"degree","type":"Card","dataType":"number"},{"propertyKey":"flaggedDegree","type":"Card","dataType":"number"},{"propertyKey":"guid","type":"Card","dataType":"string"},{"propertyKey":"cardType","type":"Card","dataType":"string"},{"propertyKey":"level","type":"Card","dataType":"string"}],"Device":[{"propertyKey":"fraudRiskDegree","type":"Device","dataType":"number"},{"propertyKey":"fraudRiskRatio","type":"Device","dataType":"number"},{"propertyKey":"flaggedDegree","type":"Device","dataType":"number"},{"propertyKey":"flaggedRatio","type":"Device","dataType":"number"},{"propertyKey":"guid","type":"Device","dataType":"string"},{"propertyKey":"os","type":"Device","dataType":"string"},{"propertyKey":"degree","type":"Device","dataType":"number"},{"propertyKey":"device","type":"Device","dataType":"string"},{"propertyKey":"louvainCommunityId","type":"Device","dataType":"bigint"}],"IP":[{"propertyKey":"fraudRiskRatio","type":"IP","dataType":"number"},{"propertyKey":"flaggedRatio","type":"IP","dataType":"number"},{"propertyKey":"fraudRiskDegree","type":"IP","dataType":"number"},{"propertyKey":"degree","type":"IP","dataType":"number"},{"propertyKey":"flaggedDegree","type":"IP","dataType":"number"},{"propertyKey":"guid","type":"IP","dataType":"string"}],"User":[{"propertyKey":"deviceDegree","type":"User","dataType":"number"},{"propertyKey":"ipDegree","type":"User","dataType":"number"},{"propertyKey":"cardDegree","type":"User","dataType":"number"},{"propertyKey":"p2pReceivedWeightedPageRank","type":"User","dataType":"number"},{"propertyKey":"p2pReceivedWeightedDegree","type":"User","dataType":"number"},{"propertyKey":"p2pSharedCardPageRank","type":"User","dataType":"number"},{"propertyKey":"p2pSentPageRank","type":"User","dataType":"number"},{"propertyKey":"communitySize","type":"User","dataType":"bigint"},{"propertyKey":"partOfCommunity","type":"User","dataType":"bigint"},{"propertyKey":"sharedIdsDegree","type":"User","dataType":"number"},{"propertyKey":"fraudMoneyTransfer","type":"User","dataType":"bigint"},{"propertyKey":"firstChargebackMtDate","type":"User","dataType":"Date"},{"propertyKey":"fraudRisk","type":"User","dataType":"bigint"},{"propertyKey":"moneyTransferErrorCancelAmount","type":"User","dataType":"number"},{"propertyKey":"louvainCommunityId","type":"User","dataType":"bigint"},{"propertyKey":"wccId","type":"User","dataType":"bigint"},{"propertyKey":"guid","type":"User","dataType":"string"}],"FlaggedUser":[{"propertyKey":"deviceDegree","type":"FlaggedUser","dataType":"number"},{"propertyKey":"ipDegree","type":"FlaggedUser","dataType":"number"},{"propertyKey":"cardDegree","type":"FlaggedUser","dataType":"number"},{"propertyKey":"p2pReceivedWeightedPageRank","type":"FlaggedUser","dataType":"number"},{"propertyKey":"p2pReceivedWeightedDegree","type":"FlaggedUser","dataType":"number"},{"propertyKey":"p2pSharedCardPageRank","type":"FlaggedUser","dataType":"number"},{"propertyKey":"p2pSentPageRank","type":"FlaggedUser","dataType":"number"},{"propertyKey":"partOfCommunity","type":"FlaggedUser","dataType":"bigint"},{"propertyKey":"sharedIdsDegree","type":"FlaggedUser","dataType":"number"},{"propertyKey":"louvainCommunityId","type":"FlaggedUser","dataType":"bigint"},{"propertyKey":"wccId","type":"FlaggedUser","dataType":"bigint"},{"propertyKey":"fraudRisk","type":"FlaggedUser","dataType":"bigint"},{"propertyKey":"communitySize","type":"FlaggedUser","dataType":"bigint"},{"propertyKey":"fraudMoneyTransfer","type":"FlaggedUser","dataType":"bigint"},{"propertyKey":"firstChargebackMtDate","type":"FlaggedUser","dataType":"Date"},{"propertyKey":"moneyTransferErrorCancelAmount","type":"FlaggedUser","dataType":"number"},{"propertyKey":"guid","type":"FlaggedUser","dataType":"string"}],"FraudRiskUser":[{"propertyKey":"deviceDegree","type":"FraudRiskUser","dataType":"number"},{"propertyKey":"ipDegree","type":"FraudRiskUser","dataType":"number"},{"propertyKey":"cardDegree","type":"FraudRiskUser","dataType":"number"},{"propertyKey":"p2pReceivedWeightedPageRank","type":"FraudRiskUser","dataType":"number"},{"propertyKey":"p2pReceivedWeightedDegree","type":"FraudRiskUser","dataType":"number"},{"propertyKey":"p2pSharedCardPageRank","type":"FraudRiskUser","dataType":"number"},{"propertyKey":"p2pSentPageRank","type":"FraudRiskUser","dataType":"number"},{"propertyKey":"communitySize","type":"FraudRiskUser","dataType":"bigint"},{"propertyKey":"partOfCommunity","type":"FraudRiskUser","dataType":"bigint"},{"propertyKey":"sharedIdsDegree","type":"FraudRiskUser","dataType":"number"},{"propertyKey":"fraudMoneyTransfer","type":"FraudRiskUser","dataType":"bigint"},{"propertyKey":"firstChargebackMtDate","type":"FraudRiskUser","dataType":"Date"},{"propertyKey":"fraudRisk","type":"FraudRiskUser","dataType":"bigint"},{"propertyKey":"moneyTransferErrorCancelAmount","type":"FraudRiskUser","dataType":"number"},{"propertyKey":"louvainCommunityId","type":"FraudRiskUser","dataType":"bigint"},{"propertyKey":"wccId","type":"FraudRiskUser","dataType":"bigint"},{"propertyKey":"guid","type":"FraudRiskUser","dataType":"string"}],"FraudSharedId":[{"propertyKey":"fraudRiskDegree","type":"FraudSharedId","dataType":"number"},{"propertyKey":"fraudRiskRatio","type":"FraudSharedId","dataType":"number"},{"propertyKey":"flaggedRatio","type":"FraudSharedId","dataType":"number"},{"propertyKey":"louvainCommunityId","type":"FraudSharedId","dataType":"bigint"},{"propertyKey":"degree","type":"FraudSharedId","dataType":"number"},{"propertyKey":"flaggedDegree","type":"FraudSharedId","dataType":"number"},{"propertyKey":"guid","type":"FraudSharedId","dataType":"string"},{"propertyKey":"cardType","type":"FraudSharedId","dataType":"string"},{"propertyKey":"level","type":"FraudSharedId","dataType":"string"}],"PredictedFraudRisk":[{"propertyKey":"deviceDegree","type":"PredictedFraudRisk","dataType":"number"},{"propertyKey":"predictedProbability","type":"PredictedFraudRisk","dataType":"number"},{"propertyKey":"ipDegree","type":"PredictedFraudRisk","dataType":"number"},{"propertyKey":"cardDegree","type":"PredictedFraudRisk","dataType":"number"},{"propertyKey":"p2pReceivedWeightedPageRank","type":"PredictedFraudRisk","dataType":"number"},{"propertyKey":"p2pReceivedWeightedDegree","type":"PredictedFraudRisk","dataType":"number"},{"propertyKey":"p2pSharedCardPageRank","type":"PredictedFraudRisk","dataType":"number"},{"propertyKey":"p2pSentPageRank","type":"PredictedFraudRisk","dataType":"number"},{"propertyKey":"communitySize","type":"PredictedFraudRisk","dataType":"bigint"},{"propertyKey":"partOfCommunity","type":"PredictedFraudRisk","dataType":"bigint"},{"propertyKey":"sharedIdsDegree","type":"PredictedFraudRisk","dataType":"number"},{"propertyKey":"fraudMoneyTransfer","type":"PredictedFraudRisk","dataType":"bigint"},{"propertyKey":"firstChargebackMtDate","type":"PredictedFraudRisk","dataType":"Date"},{"propertyKey":"fraudRisk","type":"PredictedFraudRisk","dataType":"bigint"},{"propertyKey":"moneyTransferErrorCancelAmount","type":"PredictedFraudRisk","dataType":"number"},{"propertyKey":"louvainCommunityId","type":"PredictedFraudRisk","dataType":"bigint"},{"propertyKey":"wccId","type":"PredictedFraudRisk","dataType":"bigint"},{"propertyKey":"guid","type":"PredictedFraudRisk","dataType":"string"}]},"relationshipTypes":[{"id":"P2P","name":"P2P","properties":[{"propertyKey":"transactionDateTime","type":"P2P","dataType":"DateTime"},{"propertyKey":"totalAmount","type":"P2P","dataType":"number"}],"color":"#569480","size":1,"captionKeys":["0_REL_TYPE_CAPTION_KEY"]},{"id":"HAS_CC","name":"HAS_CC","properties":[{"propertyKey":"cardDate","type":"HAS_CC","dataType":"Date"},{"propertyKey":"inverseDegreeWeight","type":"HAS_CC","dataType":"number"}],"color":"#848484","size":1,"captionKeys":["0_REL_TYPE_CAPTION_KEY"]},{"id":"USED","name":"USED","properties":[{"propertyKey":"deviceDate","type":"USED","dataType":"Date"},{"propertyKey":"inverseDegreeWeight","type":"USED","dataType":"number"}],"color":"#848484","size":1,"captionKeys":["0_REL_TYPE_CAPTION_KEY"]},{"id":"HAS_IP","name":"HAS_IP","properties":[{"propertyKey":"ipDate","type":"HAS_IP","dataType":"Date"},{"propertyKey":"inverseDegreeWeight","type":"HAS_IP","dataType":"number"}],"color":"#848484","size":1,"captionKeys":["0_REL_TYPE_CAPTION_KEY"]},{"id":"REFERRED","name":"REFERRED","properties":[],"color":"#569480","size":1,"captionKeys":["0_REL_TYPE_CAPTION_KEY"]},{"id":"P2P_WITH_SHARED_CARD","name":"P2P_WITH_SHARED_CARD","properties":[],"color":"#848484","size":1,"captionKeys":["0_REL_TYPE_CAPTION_KEY"]},{"id":"SHARED_IDS","name":"SHARED_IDS","properties":[],"color":"#848484","size":1,"captionKeys":["0_REL_TYPE_CAPTION_KEY"]},{"id":"SIMILAR_IDS","name":"SIMILAR_IDS","properties":[],"color":"#848484","size":1,"captionKeys":["0_REL_TYPE_CAPTION_KEY"]}],"palette":{"colors":["#FFE081","#C990C0","#F79767","#57C7E3","#F16667","#D9C8AE","#8DCC93","#ECB5C9","#4C8EDA","#FFC454","#DA7194","#569480","#848484","#D9D9D9"],"currentIndex":9},"createdAt":1645545791146,"lastEditedAt":1645545791146,"templates":[{"name":"Search phrase 6","id":"tmpl:1664287145835","createdAt":1664287145835,"text":"Predicted Fraud Risk Networks","cypher":"MATCH(p:PredictedFraudRisk)\nWITH COLLECT(p.wccId) AS wccIds\nMATCH(u1:User) WHERE u1.wccId IN wccIds\nMATCH(u2:User) WHERE u2.wccId IN wccIds\nWITH u1, u2\nMATCH(u1)-[r1:HAS_CC|HAS_IP|USED]->(n)<-[r2:HAS_CC|HAS_IP|USED]-(u2)\nWITH *\nOPTIONAL MATCH (u1)-[r3:P2P]-(u2)\nRETURN *","isUpdateQuery":null,"params":[],"hasCypherErrors":false},{"name":"Search phrase 5","id":"tmpl:1664284305556","createdAt":1664284305556,"text":"Community Similarity Example","cypher":"MATCH (n:User) WHERE (n.wccId IN [4616, 4932]) OR (n.guid = \"0b3f278ff6b348fb1a599479d9321cd9\")\nWITH COLLECT(n) AS nn\nUNWIND nn AS n1\nUNWIND nn AS n2\nOPTIONAL MATCH (n1)-[r1:HAS_CC|HAS_IP|USED]->(m)<-[r2:HAS_CC|HAS_IP|USED]-(n2)\nOPTIONAL MATCH(n1)-[p]-(n2)\nRETURN *","isUpdateQuery":null,"params":[],"hasCypherErrors":false},{"name":"Search phrase 4","id":"tmpl:1664278100764","createdAt":1664278100764,"text":"Louvain Community $id","cypher":"MATCH(n1 {louvainCommunityId: $id})\nMATCH(n2 {louvainCommunityId: $id})\nWITH *\nOPTIONAL MATCH (n1)-[r]-(n2)\nRETURN *","isUpdateQuery":null,"params":[{"name":"$id","dataType":"Integer","collapsed":false,"suggestionLabel":null,"suggestionProp":null,"suggestionBoolean":false,"cypher":null}],"hasCypherErrors":false},{"name":"Get User local network from Louvain Community","id":"tmpl:1664277841571","createdAt":1664277841571,"text":"Louvain User Community $id","cypher":"MATCH(u1:User{louvainCommunityId: $id})-[r1:HAS_CC|HAS_IP|USED]->(n)<-[r2:HAS_CC|HAS_IP|USED]-(u2:User{louvainCommunityId: $id})\nWITH *\nOPTIONAL MATCH (u1)-[r3:P2P]-(u2)\nRETURN *","isUpdateQuery":null,"params":[{"name":"$id","dataType":"Integer","collapsed":false,"suggestionLabel":null,"suggestionProp":null,"suggestionBoolean":false,"cypher":null}],"hasCypherErrors":false},{"name":"Search phrase 5","id":"tmpl:1645817708434","createdAt":1645817708434,"text":"User $guid","cypher":"MATCH(u:User) WHERE u.guid = $guid RETURN u","isUpdateQuery":null,"params":[{"name":"$guid","dataType":"String","collapsed":false,"suggestionLabel":null,"suggestionProp":null,"suggestionBoolean":false,"cypher":null}],"hasCypherErrors":false},{"name":"Search phrase 2","id":"tmpl:1645641852092","createdAt":1645641852092,"text":"User Component $id","cypher":"MATCH(u1:User{wccId: $id})-[r1:HAS_CC|HAS_IP|USED]->(n)<-[r2:HAS_CC|HAS_IP|USED]-(u2:User{wccId: $id})\nWITH *\nOPTIONAL MATCH (u1)-[r3:P2P]-(u2)\nRETURN *\n","isUpdateQuery":null,"params":[{"name":"$id","dataType":"Integer","collapsed":false,"suggestionLabel":null,"suggestionProp":null,"suggestionBoolean":false,"cypher":null}],"hasCypherErrors":false},{"name":"Search phrase ","id":"tmpl:1645545816275","createdAt":1645545816275,"text":"similarity top $k","cypher":"MATCH(:FraudRiskUser)<-[s:SIMILAR_IDS]-(u) WHERE NOT u:FraudRiskUser\nWITH id(u) as userId, sum(s.score) AS aggregateScore ORDER BY aggregateScore DESC LIMIT $k\nWITH collect(userId) AS userIds\nMATCH(f:FraudRiskUser)<-[s:SIMILAR_IDS]-(u) WHERE id(u) in userIds\nWITH f,s,u\nOPTIONAL MATCH (f)-[r1:HAS_CC|HAS_IP|USED]->(n)<-[r2:HAS_CC|HAS_IP|USED]-(u)\nWITH *\nOPTIONAL MATCH (f)-[p]-(u)\nRETURN *","isUpdateQuery":null,"params":[{"name":"$k","dataType":"Integer","collapsed":false,"suggestionLabel":null,"suggestionProp":null,"suggestionBoolean":false,"cypher":null}],"hasCypherErrors":false}],"hiddenRelationshipTypes":[],"hiddenCategories":[],"hideUncategorisedData":false,"isAuto":true,"parentPerspectiveId":false,"metadata":{"pathSegments":[{"source":"User","relationshipType":"SIMILAR_IDS","target":"PredictedFraudRisk"},{"source":"PredictedFraudRisk","relationshipType":"SIMILAR_IDS","target":"FraudRiskUser"},{"source":"FlaggedUser","relationshipType":"SIMILAR_IDS","target":"FlaggedUser"},{"source":"User","relationshipType":"SIMILAR_IDS","target":"User"},{"source":"FlaggedUser","relationshipType":"SIMILAR_IDS","target":"PredictedFraudRisk"},{"source":"FraudRiskUser","relationshipType":"SIMILAR_IDS","target":"User"},{"source":"FlaggedUser","relationshipType":"SIMILAR_IDS","target":"FraudRiskUser"},{"source":"PredictedFraudRisk","relationshipType":"SIMILAR_IDS","target":"PredictedFraudRisk"},{"source":"PredictedFraudRisk","relationshipType":"SIMILAR_IDS","target":"FlaggedUser"},{"source":"FraudRiskUser","relationshipType":"SIMILAR_IDS","target":"FraudRiskUser"},{"source":"PredictedFraudRisk","relationshipType":"SIMILAR_IDS","target":"User"},{"source":"FraudRiskUser","relationshipType":"SIMILAR_IDS","target":"PredictedFraudRisk"},{"source":"FlaggedUser","relationshipType":"SIMILAR_IDS","target":"User"},{"source":"FraudRiskUser","relationshipType":"SIMILAR_IDS","target":"FlaggedUser"},{"source":"User","relationshipType":"SIMILAR_IDS","target":"FlaggedUser"},{"source":"User","relationshipType":"SIMILAR_IDS","target":"FraudRiskUser"},{"source":"User","relationshipType":"HAS_IP","target":"IP"},{"source":"FraudRiskUser","relationshipType":"HAS_IP","target":"FraudSharedId"},{"source":"PredictedFraudRisk","relationshipType":"HAS_IP","target":"FraudSharedId"},{"source":"FlaggedUser","relationshipType":"HAS_IP","target":"IP"},{"source":"User","relationshipType":"HAS_IP","target":"FraudSharedId"},{"source":"FraudRiskUser","relationshipType":"HAS_IP","target":"IP"},{"source":"FlaggedUser","relationshipType":"HAS_IP","target":"FraudSharedId"},{"source":"PredictedFraudRisk","relationshipType":"HAS_IP","target":"IP"},{"source":"FlaggedUser","relationshipType":"REFERRED","target":"User"},{"source":"FraudRiskUser","relationshipType":"REFERRED","target":"FlaggedUser"},{"source":"FlaggedUser","relationshipType":"REFERRED","target":"FraudRiskUser"},{"source":"FraudRiskUser","relationshipType":"REFERRED","target":"FraudRiskUser"},{"source":"User","relationshipType":"REFERRED","target":"FlaggedUser"},{"source":"FraudRiskUser","relationshipType":"REFERRED","target":"User"},{"source":"User","relationshipType":"REFERRED","target":"FraudRiskUser"},{"source":"User","relationshipType":"REFERRED","target":"User"},{"source":"FlaggedUser","relationshipType":"REFERRED","target":"FlaggedUser"},{"source":"User","relationshipType":"P2P_WITH_SHARED_CARD","target":"FraudRiskUser"},{"source":"FlaggedUser","relationshipType":"P2P_WITH_SHARED_CARD","target":"PredictedFraudRisk"},{"source":"FlaggedUser","relationshipType":"P2P_WITH_SHARED_CARD","target":"FraudRiskUser"},{"source":"FraudRiskUser","relationshipType":"P2P_WITH_SHARED_CARD","target":"FlaggedUser"},{"source":"FlaggedUser","relationshipType":"P2P_WITH_SHARED_CARD","target":"FlaggedUser"},{"source":"FraudRiskUser","relationshipType":"P2P_WITH_SHARED_CARD","target":"FraudRiskUser"},{"source":"PredictedFraudRisk","relationshipType":"P2P_WITH_SHARED_CARD","target":"FlaggedUser"},{"source":"PredictedFraudRisk","relationshipType":"P2P_WITH_SHARED_CARD","target":"FraudRiskUser"},{"source":"PredictedFraudRisk","relationshipType":"P2P_WITH_SHARED_CARD","target":"User"},{"source":"FlaggedUser","relationshipType":"P2P_WITH_SHARED_CARD","target":"User"},{"source":"User","relationshipType":"P2P_WITH_SHARED_CARD","target":"PredictedFraudRisk"},{"source":"User","relationshipType":"P2P_WITH_SHARED_CARD","target":"FlaggedUser"},{"source":"PredictedFraudRisk","relationshipType":"P2P_WITH_SHARED_CARD","target":"PredictedFraudRisk"},{"source":"User","relationshipType":"P2P_WITH_SHARED_CARD","target":"User"},{"source":"FraudRiskUser","relationshipType":"P2P_WITH_SHARED_CARD","target":"User"},{"source":"FraudRiskUser","relationshipType":"P2P_WITH_SHARED_CARD","target":"PredictedFraudRisk"},{"source":"PredictedFraudRisk","relationshipType":"USED","target":"Device"},{"source":"User","relationshipType":"USED","target":"FraudSharedId"},{"source":"FlaggedUser","relationshipType":"USED","target":"Device"},{"source":"User","relationshipType":"USED","target":"Device"},{"source":"FlaggedUser","relationshipType":"USED","target":"FraudSharedId"},{"source":"FraudRiskUser","relationshipType":"USED","target":"Device"},{"source":"PredictedFraudRisk","relationshipType":"USED","target":"FraudSharedId"},{"source":"FraudRiskUser","relationshipType":"USED","target":"FraudSharedId"},{"source":"FlaggedUser","relationshipType":"HAS_CC","target":"Card"},{"source":"User","relationshipType":"HAS_CC","target":"FraudSharedId"},{"source":"User","relationshipType":"HAS_CC","target":"Card"},{"source":"FraudRiskUser","relationshipType":"HAS_CC","target":"Card"},{"source":"FlaggedUser","relationshipType":"HAS_CC","target":"FraudSharedId"},{"source":"FraudRiskUser","relationshipType":"HAS_CC","target":"FraudSharedId"},{"source":"PredictedFraudRisk","relationshipType":"HAS_CC","target":"Card"},{"source":"PredictedFraudRisk","relationshipType":"HAS_CC","target":"FraudSharedId"},{"source":"User","relationshipType":"SHARED_IDS","target":"PredictedFraudRisk"},{"source":"PredictedFraudRisk","relationshipType":"SHARED_IDS","target":"FraudRiskUser"},{"source":"FlaggedUser","relationshipType":"SHARED_IDS","target":"PredictedFraudRisk"},{"source":"User","relationshipType":"SHARED_IDS","target":"User"},{"source":"FlaggedUser","relationshipType":"SHARED_IDS","target":"FraudRiskUser"},{"source":"PredictedFraudRisk","relationshipType":"SHARED_IDS","target":"User"},{"source":"FraudRiskUser","relationshipType":"SHARED_IDS","target":"User"},{"source":"PredictedFraudRisk","relationshipType":"SHARED_IDS","target":"PredictedFraudRisk"},{"source":"FlaggedUser","relationshipType":"SHARED_IDS","target":"FlaggedUser"},{"source":"PredictedFraudRisk","relationshipType":"SHARED_IDS","target":"FlaggedUser"},{"source":"User","relationshipType":"SHARED_IDS","target":"FraudRiskUser"},{"source":"FraudRiskUser","relationshipType":"SHARED_IDS","target":"PredictedFraudRisk"},{"source":"User","relationshipType":"SHARED_IDS","target":"FlaggedUser"},{"source":"FraudRiskUser","relationshipType":"SHARED_IDS","target":"FraudRiskUser"},{"source":"FlaggedUser","relationshipType":"SHARED_IDS","target":"User"},{"source":"FraudRiskUser","relationshipType":"SHARED_IDS","target":"FlaggedUser"},{"source":"FlaggedUser","relationshipType":"P2P","target":"FlaggedUser"},{"source":"User","relationshipType":"P2P","target":"User"},{"source":"User","relationshipType":"P2P","target":"PredictedFraudRisk"},{"source":"FlaggedUser","relationshipType":"P2P","target":"User"},{"source":"PredictedFraudRisk","relationshipType":"P2P","target":"FlaggedUser"},{"source":"PredictedFraudRisk","relationshipType":"P2P","target":"FraudRiskUser"},{"source":"FlaggedUser","relationshipType":"P2P","target":"FraudRiskUser"},{"source":"FraudRiskUser","relationshipType":"P2P","target":"User"},{"source":"FlaggedUser","relationshipType":"P2P","target":"PredictedFraudRisk"},{"source":"User","relationshipType":"P2P","target":"FraudRiskUser"},{"source":"User","relationshipType":"P2P","target":"FlaggedUser"},{"source":"FraudRiskUser","relationshipType":"P2P","target":"FlaggedUser"},{"source":"FraudRiskUser","relationshipType":"P2P","target":"FraudRiskUser"},{"source":"PredictedFraudRisk","relationshipType":"P2P","target":"User"},{"source":"FraudRiskUser","relationshipType":"P2P","target":"PredictedFraudRisk"},{"source":"PredictedFraudRisk","relationshipType":"P2P","target":"PredictedFraudRisk"}],"indexes":[{"label":null,"type":"native","propertyKeys":[]},{"label":"FlaggedUser","type":"native","isMetadataPropIndex":true,"propertyKeys":["deviceDegree","ipDegree","cardDegree","p2pReceivedWeightedPageRank","p2pReceivedWeightedDegree","p2pSharedCardPageRank","p2pSentPageRank","partOfCommunity","sharedIdsDegree","louvainCommunityId","wccId","fraudRisk","communitySize","fraudMoneyTransfer","firstChargebackMtDate","moneyTransferErrorCancelAmount","guid"]},{"label":"FraudRiskUser","type":"native","isMetadataPropIndex":true,"propertyKeys":["deviceDegree","ipDegree","cardDegree","p2pReceivedWeightedPageRank","p2pReceivedWeightedDegree","p2pSharedCardPageRank","p2pSentPageRank","communitySize","partOfCommunity","sharedIdsDegree","fraudMoneyTransfer","firstChargebackMtDate","fraudRisk","moneyTransferErrorCancelAmount","louvainCommunityId","wccId","guid"]},{"label":"PredictedFraudRisk","type":"native","isMetadataPropIndex":true,"propertyKeys":["deviceDegree","predictedProbability","ipDegree","cardDegree","p2pReceivedWeightedPageRank","p2pReceivedWeightedDegree","p2pSharedCardPageRank","p2pSentPageRank","communitySize","partOfCommunity","sharedIdsDegree","fraudMoneyTransfer","firstChargebackMtDate","fraudRisk","moneyTransferErrorCancelAmount","louvainCommunityId","wccId","guid"]}],"stats":{"labels":{},"relationshipTypes":{"P2P":102832,"HAS_CC":128066,"USED":55026,"HAS_IP":1488949,"REFERRED":1870,"P2P_WITH_SHARED_CARD":6240,"SHARED_IDS":5316,"SIMILAR_IDS":314504}}},"version":"2.4.0"}